spotify_dbus_status.py
spotify_dbus_status-0.1.6.dist-info/METADATA
spotify_dbus_status-0.1.6.dist-info/WHEEL
spotify_dbus_status-0.1.6.dist-info/entry_points.txt
spotify_dbus_status-0.1.6.dist-info/top_level.txt
spotify_dbus_status-0.1.6.dist-info/RECORD
