Metadata-Version: 2.1
Name: spotify-dbus-status
Version: 0.1.6
Summary: Get the current spotify status from cmd line
Home-page: https://github.com/Jackevansevo/spotify-dbus-status
Author: Jack Evans
Author-email: jack@evans.gb.net
License: MIT
Platform: UNKNOWN
Classifier: Development Status :: 2 - Pre-Alpha
Classifier: Programming Language :: Python
Classifier: Programming Language :: Python :: 3
Classifier: Programming Language :: Python :: 3.5
Classifier: Programming Language :: Python :: 3.6
